senfoni/__init__.py
senfoni-0.0.1.dist-info/WHEEL
senfoni-0.0.1.dist-info/METADATA
senfoni-0.0.1.dist-info/RECORD
