Metadata-Version: 2.1
Name: senfoni
Version: 0.0.1
Summary: 
Author: rcmalli
Author-email: refikcanmalli@gmail.com
Requires-Python: >=3.8,<4.0
Classifier: Programming Language :: Python :: 3
Classifier: Programming Language :: Python :: 3.10
Classifier: Programming Language :: Python :: 3.8
Classifier: Programming Language :: Python :: 3.9
Requires-Dist: numpy (>=1.22.4,<2.0.0)
